plugin_engine/__init__.py
plugin_engine/class_registration.py
plugin_engine/dynamic_import.py
plugin_engine/plugin_importer.py
plugin_engine-1.0.0.dist-info/METADATA
plugin_engine-1.0.0.dist-info/WHEEL
plugin_engine-1.0.0.dist-info/top_level.txt
plugin_engine-1.0.0.dist-info/RECORD
