Metadata-Version: 2.1
Name: plugin-engine
Version: 1.0.0
Summary: A package for loading module-based plug-ins into memory.
Home-page: https://github.com/FluxIX/PyPluginEngine
Author: Chris Herrick
License: UNKNOWN
Project-URL: Bug Reports, https://github.com/FluxIX/PyPluginEngine/issues
Project-URL: Source, https://github.com/FluxIX/PyPluginEngine
Keywords: development plugin
Platform: UNKNOWN
Classifier: Development Status :: 5 - Production/Stable
Classifier: Intended Audience :: Developers
Classifier: Topic :: Software Development :: Build Tools
Classifier: License :: OSI Approved :: MIT License
Classifier: Programming Language :: Python :: 3
Classifier: Programming Language :: Python :: 3.6
Classifier: Programming Language :: Python :: 3.7
Classifier: Programming Language :: Python :: 3.8
Classifier: Programming Language :: Python :: 3.9
Classifier: Programming Language :: Python :: 3.10
Classifier: Programming Language :: Python :: 3 :: Only
Requires-Python: >=3.6, <4
